shiqingTools/__init__.py
shiqingTools/tools.py
shiqingTools-1.1.0.dist-info/METADATA
shiqingTools-1.1.0.dist-info/WHEEL
shiqingTools-1.1.0.dist-info/top_level.txt
shiqingTools-1.1.0.dist-info/RECORD
