Metadata-Version: 2.1
Name: shiqingTools
Version: 1.1.0
Summary: some personal tools
Home-page: https://github.com/buyizhiyou
Author: buyizhiyou
Author-email: 2557040812@qq.com
License: MIT
